{
	"name": "extPrototype",
	"version": "1.0.0.0",
	"description": "Library for nexacro platform17",
	"license": "",
	"scripts": [
        "extPrototype/ChUtilM.js",
        "extPrototype/Frame.js",
        "extPrototype/Util.js",
        "extPrototype/Transaction.js",
        "extPrototype/Validation.js",
        "extPrototype/Popup.js",
        "extPrototype/MultiLanguage.js",
        "extPrototype/File.js",
        "extPrototype/Message.js",
        "extPrototype/Grid.js",
        "extPrototype/Excel.js",
        "extPrototype/ExtFileUpDownload.js",
        "extPrototype/Comp.js", 
        "extPrototype/PivotGrid.js",
        "extPrototype/Mobile.js",
		"extPrototype/Sha.js",
		"extPrototype/ChJobCommonM.js"		
	]
}